README.md
README.rst
setup.py
jatnipy/Experiment.py
jatnipy/__init__.py
jatnipy/dataRunParameters.py
jatnipy/find.py
jatnipy/ind.py
jatnipy/normv.py
jatnipy/optimalP.py
jatnipy/stabilize_stabilize_matrix.py
jatnipy.egg-info/PKG-INFO
jatnipy.egg-info/SOURCES.txt
jatnipy.egg-info/dependency_links.txt
jatnipy.egg-info/not-zip-safe
jatnipy.egg-info/requires.txt
jatnipy.egg-info/top_level.txt
jatnipy/Methods/Glmnet.py
jatnipy/Methods/Lasso.py
jatnipy/Methods/RInorm.py
jatnipy/Methods/RNI.py
jatnipy/Methods/lsco.py
jatnipy/analyse/CompareModels.py
jatnipy/analyse/DataAnalysis.py
jatnipy/analyse/DataModel.py
jatnipy/analyse/Dataset_fetch.py
jatnipy/analyse/Dataset_function.py
jatnipy/analyse/Model.py
jatnipy/datastruct/Dataset.py
jatnipy/datastruct/Exchange.py
jatnipy/datastruct/Exchange_fetch.py
jatnipy/datastruct/Network.py
jatnipy/datastruct/RSS.py
jatnipy/datastruct/cutSym.py
jatnipy/datastruct/expectedSNRv.py
jatnipy/datastruct/obj_dict.py
jatnipy/datastruct/optimalRandomP.py
jatnipy/datastruct/randomNet.py
jatnipy/datastruct/replace.py
jatnipy/datastruct/scalefree.py
jatnipy/datastruct/smallworld.py
jatnipy/datastruct/stabilize.py
jatnipy/datastruct/weightP.py